sdk/__init__.py
sdk/admitad.py
sdk/analytics.py
sdk/barcode_recognizer.py
sdk/base.py
sdk/cash_register.py
sdk/click_again.py
sdk/client.py
sdk/cryptopro.py
sdk/devino.py
sdk/elk.py
sdk/face_detector.py
sdk/gift.py
sdk/gigtest.py
sdk/mis/__init__.py
sdk/mis/client.py
sdk/mis/crm.py
sdk/mis/lab.py
sdk/mis/lmk.py
sdk/mis/mobil.py
sdk/mis/samd.py
sdk/mis/standalone.py
sdk/mis/widgets.py
sdk/mobile_backend.py
sdk/notemaster.py
sdk/notification.py
sdk/nsirosminzdrav.py
sdk/pbxrt.py
sdk/personal.py
sdk/pre_record.py
sdk/prodoctorov.py
sdk/reestr.py
sdk/roistat.py
sdk/samd.py
sdk/site_mobilmed.py
sdk/skillaz.py
sdk/sms.py
sdk/utils/__init__.py
sdk/utils/django_request_id.py
sdk/yandex_courier.py
mm_sdk-0.1.455.dist-info/WHEEL
mm_sdk-0.1.455.dist-info/METADATA
mm_sdk-0.1.455.dist-info/RECORD
